mps-0.20.16.dist-info/metadata.json
mps-0.20.16.dist-info/entry_points.txt
mps-0.20.16.dist-info/WHEEL
mps-0.20.16.dist-info/DESCRIPTION.rst
mps-0.20.16.dist-info/METADATA
mps-0.20.16.dist-info/RECORD
mps-0.20.16.dist-info/top_level.txt
mps_pkg/__init__.py
mps_pkg/main.py
